UGrid-0.13.0.data/purelib/ugrid/UGridApi.dll
UGrid-0.13.0.data/purelib/ugrid/__init__.py
UGrid-0.13.0.data/purelib/ugrid/c_structures.py
UGrid-0.13.0.data/purelib/ugrid/concrt140.dll
UGrid-0.13.0.data/purelib/ugrid/errors.py
UGrid-0.13.0.data/purelib/ugrid/hdf.dll
UGrid-0.13.0.data/purelib/ugrid/hdf5.dll
UGrid-0.13.0.data/purelib/ugrid/hdf5_cpp.dll
UGrid-0.13.0.data/purelib/ugrid/hdf5_hl.dll
UGrid-0.13.0.data/purelib/ugrid/hdf5_hl_cpp.dll
UGrid-0.13.0.data/purelib/ugrid/hdf5_tools.dll
UGrid-0.13.0.data/purelib/ugrid/jpeg.dll
UGrid-0.13.0.data/purelib/ugrid/libcurl.dll
UGrid-0.13.0.data/purelib/ugrid/mfhdf.dll
UGrid-0.13.0.data/purelib/ugrid/msvcp140.dll
UGrid-0.13.0.data/purelib/ugrid/netcdf.dll
UGrid-0.13.0.data/purelib/ugrid/py_structures.py
UGrid-0.13.0.data/purelib/ugrid/ugrid.py
UGrid-0.13.0.data/purelib/ugrid/utils.py
UGrid-0.13.0.data/purelib/ugrid/vcruntime140.dll
UGrid-0.13.0.data/purelib/ugrid/version.py
UGrid-0.13.0.data/purelib/ugrid/xdr.dll
UGrid-0.13.0.data/purelib/ugrid/zlib1.dll
UGrid-0.13.0.dist-info/LICENSE
UGrid-0.13.0.dist-info/METADATA
UGrid-0.13.0.dist-info/WHEEL
UGrid-0.13.0.dist-info/top_level.txt
UGrid-0.13.0.dist-info/RECORD
