Metadata-Version: 2.1
Name: UGrid
Version: 0.13.0
Summary: `UGrid` is a library to write and read UGrid files.
Home-page: https://github.com/Deltares/UGridPy
Author: Luca Carniato
Author-email: luca.carniato@deltares.nl
License: MIT
Platform: Windows
Platform: Linux
Classifier: Topic :: Scientific/Engineering :: Mathematics
Requires-Python: >=3.8
Requires-Dist: numpy
Requires-Dist: meshkernel
Provides-Extra: docs
Requires-Dist: sphinx ; extra == 'docs'
Requires-Dist: sphinx-book-theme ; extra == 'docs'
Requires-Dist: myst-nb ; extra == 'docs'
Provides-Extra: lint
Requires-Dist: flake8 ; extra == 'lint'
Requires-Dist: black (==21.4b1) ; extra == 'lint'
Requires-Dist: isort ; extra == 'lint'
Provides-Extra: tests
Requires-Dist: pytest ; extra == 'tests'
Requires-Dist: pytest-cov ; extra == 'tests'
Requires-Dist: nbval ; extra == 'tests'
